proj.vhdl
library ieee;
use ieee.std_logic_1164.all;
 entity proj is 
 port ( input : in std_logic_vector(3 downto 0); 
        
         output : out std_logic_vector(6 downto 0)); 
 end proj;

 architecture arch of proj is 
 begin
    
     with input select
         output <= "0000001" when "0000",  -- 0
                   "1001111" when "0001",  -- 1
                   "0010010" when "0010",  -- 2
                   "0000110" when "0011",  -- 3
                   "1001100" when "0100",  -- 4
                   "0100100" when "0101",  -- 5
                   "0100000" when "0110",  -- 6
                   "0001111" when "0111",  -- 7
                   "0000000" when "1000",  -- 8
                   "0000100" when "1001",  -- 9
                   "1110111" when "1010",  -- 10
                   "0011111" when "1011",  -- 11
                   "1001110" when "1100",  -- 12
                   "0111101" when "1101",  -- 13
                   "1001111" when "1110",  -- 14
                   "1000111" when "1111",  -- 15
                   "1111111" when others;  -- default (all segments off)
  end arch;

testbench.vhd
library ieee;
use ieee.std_logic_1164.all;
use ieee.numeric_std.all;

entity testbench is
end entity;

architecture tb of testbench is
    -- Signals to connect to the design
    signal input_sig  : std_logic_vector(3 downto 0) := "0000";
    signal output_sig : std_logic_vector(6 downto 0);
begin
    -- Instantiate your design
    uut: entity work.proj
        port map (
            input  => input_sig,
            output => output_sig
        );

    -- Stimulus process: cycle through all inputs
    stim_process: process
    begin
        for i in 0 to 15 loop
            input_sig <= std_logic_vector(to_unsigned(i, 4));
            wait for 20 ns;  -- wait time per input
        end loop;

        -- End simulation
assert false report "End of simulation" severity note;
    end process;

end architecture;

wave.vcd
$date
  Sun Nov 23 14:38:58 2025
$end
$version
  GHDL v0
$end
$timescale
  1 fs
$end
$scope module standard $end
$upscope $end
$scope module std_logic_1164 $end
$upscope $end
$scope module numeric_std $end
$upscope $end
$scope module testbench $end
$var reg 4 ! input_sig[3:0] $end
$var reg 7 " output_sig[6:0] $end
$scope module uut $end
$var reg 4 # input[3:0] $end
$var reg 7 $ output[6:0] $end
$upscope $end
$upscope $end
$enddefinitions $end
#0
b0000 !
b0000001 "
b0000 #
b0000001 $
#20000000
b0001 !
b1001111 "
b0001 #
b1001111 $
#40000000
b0010 !
b0010010 "
b0010 #
b0010010 $
#60000000
b0011 !
b0000110 "
b0011 #
b0000110 $
#80000000
b0100 !
b1001100 "
b0100 #
b1001100 $
#100000000
b0101 !
b0100100 "
b0101 #
b0100100 $
#120000000
b0110 !
b0100000 "
b0110 #
b0100000 $
#140000000
b0111 !
b0001111 "
b0111 #
b0001111 $
#160000000
b1000 !
b0000000 "
b1000 #
b0000000 $
#180000000
b1001 !
b0000100 "
b1001 #
b0000100 $
#200000000
b1010 !
b1110111 "
b1010 #
b1110111 $
#220000000
b1011 !
b0011111 "
b1011 #
b0011111 $
#240000000
b1100 !
b1001110 "
b1100 #
b1001110 $
#260000000
b1101 !
b0111101 "
b1101 #
b0111101 $
#280000000
b1110 !
b1001111 "
b1110 #
b1001111 $
#300000000
b1111 !
b1000111 "
b1111 #
b1000111 $
